AUTHORS
CITATION.bib
CMakeLists.txt
COPYING
ChangeLog
FindSimGrid.cmake
LICENSE-LGPL-2.1
MANIFEST.in
MANIFEST.in.in
NEWS
README.md
setup.py
doc/doxygen/FAQ.doc
doc/doxygen/inside_extending.doc
doc/doxygen/inside_release.doc
doc/doxygen/outcomes_vizu.doc
doc/doxygen/uhood.doc
doc/doxygen/uhood_switch.doc
docs/Build.sh
docs/README.md
docs/find-missing.ignore
docs/find-missing.py
docs/requirements.txt
docs/bin/extract_logs_hierarchy.pl
docs/manpages/smpicc.1
docs/manpages/smpicxx.1
docs/manpages/smpif90.1
docs/manpages/smpiff.1
docs/manpages/smpirun.1
docs/manpages/tesh.pod
docs/source/Calibrating_the_models.rst
docs/source/Configuring_SimGrid.rst
docs/source/Contributors_Documentation.rst
docs/source/Deploying_your_application.rst
docs/source/Design_goals.rst
docs/source/Doxyfile
docs/source/Examples.rst
docs/source/Experimental_setup.rst
docs/source/Installing_SimGrid.rst
docs/source/Introduction.rst
docs/source/Modeling_howtos.rst
docs/source/Models.rst
docs/source/Outcomes.rst
docs/source/Platform.rst
docs/source/Platform_cpp.rst
docs/source/Platform_examples.rst
docs/source/Platform_routing.rst
docs/source/Plugins.rst
docs/source/Release_Notes.rst
docs/source/Start_your_own_project.rst
docs/source/The_XBT_toolbox.rst
docs/source/Tutorial_Algorithms.rst
docs/source/Tutorial_DAG.rst
docs/source/Tutorial_MPI_Applications.rst
docs/source/Tutorial_Model-checking.rst
docs/source/XML_reference.rst
docs/source/app_s4u.rst
docs/source/app_smpi.rst
docs/source/application.rst
docs/source/community.rst
docs/source/conf.py
docs/source/index.rst
docs/source/intl.rst
docs/source/_ext/showfile.css
docs/source/_ext/showfile.js
docs/source/_ext/showfile.py
docs/source/_static/css/custom.css
docs/source/_templates/breadcrumbs.html
docs/source/img/battery_degradation.svg
docs/source/img/dag.svg
docs/source/img/dag1.svg
docs/source/img/dag2.svg
docs/source/img/design-scheduling-parallel.svg
docs/source/img/design-scheduling-simulatedtime.svg
simgrid.egg-info/PKG-INFO
simgrid.egg-info/SOURCES.txt
simgrid.egg-info/dependency_links.txt
simgrid.egg-info/not-zip-safe
simgrid.egg-info/requires.txt
simgrid.egg-info/top_level.txt
